res.v
module par (input clk,
input rst,
input [2:0]data_in,
input mode,
input valid,
output reg parity_ok);

parameter even_state = 0;
parameter odd_state = 1'b1;


reg state;
integer i;

always@(posedge clk or posedge rst )
begin
    if(rst)
 begin
        state<= even_state;
        parity_ok <= 1'b0;
 end
    else if(valid) 
    begin
        
        state = even_state; 
        for ( i=0 ;i<4 ; i++ ) 
        begin
            if(data_in[i]) 
                state = ~state ;
        end
                
        
       
        if(mode)
        begin
            case (state)
             even_state: parity_ok <= 0;
             odd_state: parity_ok <= 1'b1; 
             default: parity_ok <= 0; 
            endcase
             
        end 

             else 
        begin
                case (state)
             even_state: parity_ok <= 1'b1;
             odd_state: parity_ok <= 0; 
             default: parity_ok <= 0; 
            endcase
        end
    end
    else
    begin
        parity_ok <= 1'b0; 
    end
   
end
endmodule

tb.v
`timescale 1ps/1ps
`include "res.v"
module tb ();
    reg clk;
    reg rst;
    reg  [2:0] data_in;
    reg mode;
    reg valid;
   wire parity_ok;

par u1(.clk(clk),
        .rst(rst),
        .data_in(data_in),
        .mode(mode),
        .valid(valid),
        .parity_ok(parity_ok)
    );
    initial
 begin
        clk = 0;
        forever #5 clk = ~clk; 
 end
  
    initial 
begin
   
        
        rst =0;
        data_in =0;
        mode=0;
        valid = 1;
        #10;
        rst =1;
        data_in =0;
        mode=1;
        valid = 0;
        #10;
  rst =0;
        data_in =1;
        mode=0;
        valid = 0;
        #10;
  rst =1;
        data_in =1;
        mode=1;
        valid = 1;
        #10;
  rst =0;
        data_in =2;
        mode=0;
        valid = 0;
        #10;
  rst =0;
        data_in =2;
        mode=1;
        valid = 1;
        #10;
  rst = 0;
        data_in =3;
        mode=0;
        valid = 1;
        #10;
  rst = 0;
        data_in =3;
        mode=1;
        valid = 0;
        #10;
  rst =1;
        data_in =4;
        mode=0;
        valid = 1;  
        #10;
    rst =1;
        data_in =4;
        mode=1;
        valid = 0;
        #10;
    rst =0;
        data_in =5;
        mode=0;
        valid = 1;
        #10;
    rst =0;
        data_in =5;
        mode=1;
        valid = 1;
        #10;
    rst =0;
        data_in =6;
        mode=0;
        valid = 1;
        #10;
    rst =1;
        data_in =6;
        mode=1;
        valid = 1;
        #10;
    rst =1;
        data_in =7;
        mode=0;
        valid = 0;
        #10;
    rst =1;
        data_in =7;
        mode=1;
        valid = 1;
        #10;
    rst =0;
        data_in =8;
        mode=0;
        valid = 1;
        #10;
    rst =0;
        data_in =8;
        mode=1;
        valid = 0;
        #10;
                $finish;        

end

    initial begin
        $dumpfile("parity_checker_tb.vcd");
        $dumpvars(0, tb);
    end 




initial begin
  $monitor("$time =%0t,clk =  %b,rst=%b,data_in=%b,mode = %b, valid = %b,  parity_ok = %b",$time,clk,rst,data_in,mode,valid,parity_ok);
  end
    
endmodule

parity_checker_tb.vcd
$date
	Sun Aug  3 22:36:20 2025
$end
$version
	Icarus Verilog
$end
$timescale
	1ps
$end
$scope module tb $end
$var wire 1 ! parity_ok $end
$var reg 1 " clk $end
$var reg 3 # data_in [2:0] $end
$var reg 1 $ mode $end
$var reg 1 % rst $end
$var reg 1 & valid $end
$scope module u1 $end
$var wire 1 " clk $end
$var wire 3 ' data_in [2:0] $end
$var wire 1 $ mode $end
$var wire 1 % rst $end
$var wire 1 & valid $end
$var reg 1 ! parity_ok $end
$var reg 1 ( state $end
$var integer 32 ) i [31:0] $end
$upscope $end
$upscope $end
$enddefinitions $end
#0
$dumpvars
bx )
x(
b0 '
1&
0%
0$
b0 #
0"
x!
$end
#5
1!
b100 )
0(
1"
#10
0!
0"
0&
1$
1%
#15
1"
#20
0"
0$
b1 #
b1 '
0%
#25
1"
#30
0"
1&
1$
1%
#35
1"
#40
0"
0&
0$
b10 #
b10 '
0%
#45
1"
#50
0"
1&
1$
#55
1!
1(
b100 )
1"
#60
0"
0$
b11 #
b11 '
#65
b100 )
0(
1"
#70
0"
0&
1$
#75
0!
1"
#80
0"
1&
0$
b100 #
b100 '
1%
#85
1"
#90
0"
0&
1$
#95
1"
#100
0"
1&
0$
b101 #
b101 '
0%
#105
1!
0(
b100 )
1"
#110
0"
1$
#115
0!
0(
b100 )
1"
#120
0"
0$
b110 #
b110 '
#125
1!
0(
b100 )
1"
#130
0!
0"
1$
1%
#135
1"
#140
0"
0&
0$
b111 #
b111 '
#145
1"
#150
0"
1&
1$
#155
1"
#160
0"
0$
b0 #
b0 '
0%
#165
1!
b100 )
1"
#170
0"
0&
1$
#175
0!
1"
